{
  "waypoints": {
    "oven":           { "x": 9.5,  "y": 15.8, "room": "kitchen", "station": true,  "facing": "up" },
    "burner1":        { "x": 17.0, "y": 15.8, "room": "kitchen", "station": true,  "facing": "up" },
    "cutting_board":  { "x": 30.5, "y": 15.8, "room": "kitchen", "station": true,  "facing": "up" },
    "spice_rack":     { "x": 40.1, "y": 15.8, "room": "kitchen", "station": true,  "facing": "up" },
    "fridge":         { "x": 44.0, "y": 15.8, "room": "kitchen", "station": true,  "facing": "up" },
    "kitchen_center": { "x": 26.0, "y": 19.8, "room": "kitchen", "station": false, "facing": "down" },
    "plating_area":   { "x": 28.6, "y": 19.8, "room": "kitchen", "station": true,  "facing": "down" }
  },
  "edges": [
    ["oven",          "kitchen_center"],
    ["burner1",       "kitchen_center"],
    ["cutting_board", "kitchen_center"],
    ["spice_rack",    "kitchen_center"],
    ["fridge",        "kitchen_center"],
    ["plating_area",  "kitchen_center"]
  ],
  "room_meta": {
    "kitchen":     { "exit": null, "entry": "kitchen_center" },
    "dining_hall": { "exit": null, "entry": null },
    "bedroom":     { "exit": null, "entry": null },
    "living_room": { "exit": null, "entry": null }
  }
}
